README.txt
cfgtodict.py
setup.py
cfgtodict.egg-info/PKG-INFO
cfgtodict.egg-info/SOURCES.txt
cfgtodict.egg-info/dependency_links.txt
cfgtodict.egg-info/top_level.txt