Metadata-Version: 1.1
Name: cfgtodict
Version: 0.1.1
Summary: A simple class for converting a *.cfg file to a Python Dictionary
Home-page: https://github.com/joelklabo/cfgtodict
Author: Joel Klabo
Author-email: joelklabo@gmail.com
License: MIT
Keywords: config dictionary utilities
Platform: UNKNOWN
Classifier: Development Status :: 4 - Beta
Classifier: Intended Audience :: Developers
Classifier: License :: OSI Approved :: MIT License
Classifier: Programming Language :: Python :: 3
Classifier: Programming Language :: Python :: 3.2
Classifier: Programming Language :: Python :: 3.3
Classifier: Programming Language :: Python :: 3.4
